growattServer/__init__.py
growattServer/base_api.py
growattServer/exceptions.py
growattServer/open_api_v1.py
growattserver-1.9.0.dist-info/licenses/LICENSE
growattserver-1.9.0.dist-info/METADATA
growattserver-1.9.0.dist-info/WHEEL
growattserver-1.9.0.dist-info/top_level.txt
growattserver-1.9.0.dist-info/RECORD
