Metadata-Version: 2.4
Name: growattServer
Version: 1.9.0
Summary: A package to talk to growatt server
Home-page: https://github.com/indykoning/PyPi_GrowattServer
Author: IndyKoning
Author-email: indykoningnl@gmail.com
License: MIT
Classifier: Programming Language :: Python :: 3
Classifier: License :: OSI Approved :: MIT License
Classifier: Operating System :: OS Independent
License-File: LICENSE
Requires-Dist: requests
Dynamic: author
Dynamic: author-email
Dynamic: classifier
Dynamic: description
Dynamic: description-content-type
Dynamic: home-page
Dynamic: license
Dynamic: license-file
Dynamic: requires-dist
Dynamic: summary
